[ {
  "emp_no" : 10322,
  "first_name" : "Isamu",
  "last_name" : "Dahlbom"
}, {
  "emp_no" : 10324,
  "first_name" : "Bernardo",
  "last_name" : "Rouquie"
}, {
  "emp_no" : 10327,
  "first_name" : "Roded",
  "last_name" : "Facello"
}, {
  "emp_no" : 10328,
  "first_name" : "Serenella",
  "last_name" : "Kawashima"
}, {
  "emp_no" : 10333,
  "first_name" : "Snehasis",
  "last_name" : "Dymetman"
}, {
  "emp_no" : 10342,
  "first_name" : "Stella",
  "last_name" : "Hiroyama"
}, {
  "emp_no" : 10345,
  "first_name" : "Arra",
  "last_name" : "Ratnakar"
}, {
  "emp_no" : 10352,
  "first_name" : "Erzsebet",
  "last_name" : "Ohori"
}, {
  "emp_no" : 10358,
  "first_name" : "Qunsheng",
  "last_name" : "Tagansky"
}, {
  "emp_no" : 10359,
  "first_name" : "Heekeun",
  "last_name" : "Sambasivam"
} ]